mandrake_db/__init__.py
mandrake_db/cli/__init__.py
mandrake_db/config/__init__.py
mandrake_db/config/environment.py
mandrake_db/core/crud/__init__.py
mandrake_db/core/crud/json_db.py
mandrake_db/core/crud/mongo_db.py
mandrake_db/core/models/__init__.py
mandrake_db/core/query_builders/__init__.py
mandrake_db/core/query_builders/json_db.py
mandrake_db/core/query_builders/mongo_db.py
mandrake_db-0.1.0.dist-info/METADATA
mandrake_db-0.1.0.dist-info/WHEEL
mandrake_db-0.1.0.dist-info/RECORD
